{
  "text" :"Jane Doe is a software engineer.\nShe works at Acme.\n‍🧙‍♀️✨ emojis!\nPortsmouth, NH",
  "annotations": [
      {"start": 0, "end": 63, "label": "*"},
      {"start": 0, "end": 8, "label": "PERSON"},
      {"start": 14, "end": 31, "label": "OCCUPATION"},
      {"start": 31, "end": 34, "label": "MULTILINE"},
      {"start": 31, "end": 36, "label": "MULTILINE"},
      {"start": 33, "end": 36, "label": "PERSON"},
      {"start": 46, "end": 50, "label": "ORGANIZATION"},
      {"start": 52, "end": 56, "label": "EMOJIS"},
      {"start": 52, "end": 54, "label": "EMOJI"},
      {"start": 54, "end": 56, "label": "EMOJI"},
      {"start": 67, "end": 77, "label": "CITY"},
      {"start": 79, "end": 81, "label": "STATE"},
      {"start": 67, "end": 81, "label": "LOCATION"}
  ]
}
